README
setup.py
scLVM/__init__.py
scLVM/core.py
scLVM/gp_clvm.py
scLVM/gp_clvm_test.py
scLVM.egg-info/PKG-INFO
scLVM.egg-info/SOURCES.txt
scLVM.egg-info/dependency_links.txt
scLVM.egg-info/pbr.json
scLVM.egg-info/requires.txt
scLVM.egg-info/top_level.txt
scLVM/utils/__init__.py
scLVM/utils/barplot.py
scLVM/utils/misc.py
scLVM/utils/plot_format.py