Metadata-Version: 1.0
Name: scLVM
Version: 0.1.5
Summary: scLVM
Home-page: https://github.com/PMBio/scLVM
Author: Florian Buettner, F Paolo Casale, Oliver Stegle
Author-email: scLVM-dev@ebi.ac.uk
License: Apache 2.0
Keywords: single-cell RNA-seq, latent variable model, Variance compoennt modelling
Platform: UNKNOWN
